nodepad/__init__.py
nodepad/documenter.py
nodepad/format.py
nodepad/generate_docs.py
nodepad/interface.py
nodepad/markdown.py
nodepad/panel.py
nodepad/pref.py
nodepad/style_generator.py
nodepad/utils.py
nodepad-0.2.0.dist-info/licenses/LICENSE
nodepad-0.2.0.dist-info/METADATA
nodepad-0.2.0.dist-info/WHEEL
nodepad-0.2.0.dist-info/top_level.txt
nodepad-0.2.0.dist-info/RECORD
