Metadata-Version: 2.4
Name: nodepad
Version: 0.2.0
Summary: Generate node group documentation from Blender files
Maintainer-email: Brady Johnston <brady.johnston@me.com>
Project-URL: Homepage, https://bradyajohnston.github.io/nodepad
Project-URL: Repository, https://github.com/bradyajohnston/nodepad
Project-URL: Documentation, https://bradyajohnston.github.io/nodepad
License-File: LICENSE
Requires-Dist: numpy<2.0,>1.26
Requires-Dist: click>=8.0
Provides-Extra: bpy
Requires-Dist: bpy>=4.2; extra == "bpy"
Provides-Extra: docs
Requires-Dist: quartodoc; extra == "docs"
Requires-Dist: tomlkit; extra == "docs"
Requires-Dist: jupyter; extra == "docs"
Provides-Extra: test
Requires-Dist: pytest; extra == "test"
Requires-Dist: pytest-cov; extra == "test"
Requires-Dist: syrupy; extra == "test"
Requires-Dist: scipy; extra == "test"
Provides-Extra: dev
Requires-Dist: pytest; extra == "dev"
Requires-Dist: pytest-cov; extra == "dev"
Requires-Dist: syrupy; extra == "dev"
Requires-Dist: scipy; extra == "dev"
Requires-Dist: fake-bpy-module; extra == "dev"
Dynamic: license-file
